{
	"format_version": "1.12.0",
	"minecraft:geometry": [
		{
			"description": {
				"identifier": "geometry.Miner_MK1_anim",
				"texture_width": 96,
				"texture_height": 64,
				"visible_bounds_width": 6,
				"visible_bounds_height": 9,
				"visible_bounds_offset": [0, 3.5, 0]
			},
			"bones": [
				{
					"name": "Miner_MK1",
					"pivot": [0, 8, 0]
				},
				{
					"name": "body",
					"parent": "Miner_MK1",
					"pivot": [0, 8, 0],
					"cubes": [
						{
							"origin": [-5.5, 23.5, -5.5],
							"size": [11, 17, 11],
							"pivot": [0, 24, 0],
							"rotation": [0, -45, 0],
							"uv": {
								"north": {"uv": [64, 0], "uv_size": [4, 2]},
								"east": {"uv": [64, 0], "uv_size": [4, 2]},
								"south": {"uv": [64, 0], "uv_size": [4, 2]},
								"west": {"uv": [64, 0], "uv_size": [4, 2]},
								"up": {"uv": [68, 4], "uv_size": [-4, -4]},
								"down": {"uv": [96, 32], "uv_size": [-32, -32]}
							}
						},
						{
							"origin": [-5.5, 23.5, -5.5],
							"size": [11, 17, 11],
							"uv": {
								"north": {"uv": [0, 32], "uv_size": [4, 2]},
								"east": {"uv": [0, 32], "uv_size": [4, 2]},
								"south": {"uv": [0, 32], "uv_size": [4, 2]},
								"west": {"uv": [0, 32], "uv_size": [4, 2]},
								"up": {"uv": [4, 36], "uv_size": [-4, -4]},
								"down": {"uv": [4, 44], "uv_size": [-4, -4]}
							}
						}
					]
				},
				{
					"name": "group2",
					"parent": "body",
					"pivot": [-2, 23, 0],
					"cubes": [
						{
							"origin": [-2.5, 22.5, -7.75],
							"size": [5, 1, 15.5],
							"uv": {
								"north": {"uv": [0, 32], "uv_size": [4, 2]},
								"east": {"uv": [0, 32], "uv_size": [4, 2]},
								"south": {"uv": [0, 32], "uv_size": [4, 2]},
								"west": {"uv": [0, 32], "uv_size": [4, 2]},
								"up": {"uv": [4, 36], "uv_size": [-4, -4]},
								"down": {"uv": [4, 44], "uv_size": [-4, -4]}
							}
						},
						{
							"origin": [-2.5, 22.5, -7.75],
							"size": [5, 1, 15.5],
							"pivot": [0, 23, 0],
							"rotation": [0, -45, 0],
							"uv": {
								"north": {"uv": [0, 32], "uv_size": [4, 2]},
								"east": {"uv": [0, 32], "uv_size": [4, 2]},
								"south": {"uv": [0, 32], "uv_size": [4, 2]},
								"west": {"uv": [0, 32], "uv_size": [4, 2]},
								"up": {"uv": [4, 36], "uv_size": [-4, -4]},
								"down": {"uv": [4, 44], "uv_size": [-4, -4]}
							}
						},
						{
							"origin": [-7.75, 22.5, -2.5],
							"size": [15.5, 1, 5],
							"pivot": [0, 23, 0],
							"rotation": [0, -45, 0],
							"uv": {
								"north": {"uv": [0, 32], "uv_size": [4, 2]},
								"east": {"uv": [0, 32], "uv_size": [4, 2]},
								"south": {"uv": [0, 32], "uv_size": [4, 2]},
								"west": {"uv": [0, 32], "uv_size": [4, 2]},
								"up": {"uv": [4, 36], "uv_size": [-4, -4]},
								"down": {"uv": [4, 44], "uv_size": [-4, -4]}
							}
						},
						{
							"origin": [-7.75, 22.5, -2.5],
							"size": [15.5, 1, 5],
							"pivot": [0, 23, 0],
							"rotation": [0, 22.5, 0],
							"uv": {
								"north": {"uv": [0, 32], "uv_size": [4, 2]},
								"east": {"uv": [0, 32], "uv_size": [4, 2]},
								"south": {"uv": [0, 32], "uv_size": [4, 2]},
								"west": {"uv": [0, 32], "uv_size": [4, 2]},
								"up": {"uv": [4, 36], "uv_size": [-4, -4]},
								"down": {"uv": [4, 44], "uv_size": [-4, -4]}
							}
						},
						{
							"origin": [-2.5, 22.5, -7.75],
							"size": [5, 1, 15.5],
							"pivot": [0, 23, 0],
							"rotation": [0, -22.5, 0],
							"uv": {
								"north": {"uv": [0, 32], "uv_size": [4, 2]},
								"east": {"uv": [0, 32], "uv_size": [4, 2]},
								"south": {"uv": [0, 32], "uv_size": [4, 2]},
								"west": {"uv": [0, 32], "uv_size": [4, 2]},
								"up": {"uv": [4, 36], "uv_size": [-4, -4]},
								"down": {"uv": [4, 44], "uv_size": [-4, -4]}
							}
						},
						{
							"origin": [-2.5, 22.5, -7.75],
							"size": [5, 1, 15.5],
							"pivot": [0, 23, 0],
							"rotation": [0, 22.5, 0],
							"uv": {
								"north": {"uv": [0, 32], "uv_size": [4, 2]},
								"east": {"uv": [0, 32], "uv_size": [4, 2]},
								"south": {"uv": [0, 32], "uv_size": [4, 2]},
								"west": {"uv": [0, 32], "uv_size": [4, 2]},
								"up": {"uv": [4, 36], "uv_size": [-4, -4]},
								"down": {"uv": [4, 44], "uv_size": [-4, -4]}
							}
						},
						{
							"origin": [-7.75, 22.5, -2.5],
							"size": [15.5, 1, 5],
							"pivot": [0, 23, 0],
							"rotation": [0, -22.5, 0],
							"uv": {
								"north": {"uv": [0, 32], "uv_size": [4, 2]},
								"east": {"uv": [0, 32], "uv_size": [4, 2]},
								"south": {"uv": [0, 32], "uv_size": [4, 2]},
								"west": {"uv": [0, 32], "uv_size": [4, 2]},
								"up": {"uv": [4, 36], "uv_size": [-4, -4]},
								"down": {"uv": [4, 44], "uv_size": [-4, -4]}
							}
						},
						{
							"origin": [-7.75, 22.5, -2.5],
							"size": [15.5, 1, 5],
							"uv": {
								"north": {"uv": [0, 32], "uv_size": [4, 2]},
								"east": {"uv": [0, 32], "uv_size": [4, 2]},
								"south": {"uv": [0, 32], "uv_size": [4, 2]},
								"west": {"uv": [0, 32], "uv_size": [4, 2]},
								"up": {"uv": [4, 36], "uv_size": [-4, -4]},
								"down": {"uv": [4, 44], "uv_size": [-4, -4]}
							}
						}
					]
				},
				{
					"name": "tige_head",
					"parent": "Miner_MK1",
					"pivot": [0, 8, 0]
				},
				{
					"name": "head",
					"parent": "tige_head",
					"pivot": [0, 2.5, 0],
					"cubes": [
						{
							"origin": [-2, 9, -2],
							"size": [4, 1, 4],
							"pivot": [0, 9.5, 0],
							"rotation": [0, -45, 0],
							"uv": {
								"north": {"uv": [0, 0], "uv_size": [4, 2]},
								"east": {"uv": [0, 0], "uv_size": [4, 2]},
								"south": {"uv": [0, 0], "uv_size": [4, 2]},
								"west": {"uv": [0, 0], "uv_size": [4, 2]},
								"up": {"uv": [4, 4], "uv_size": [-4, -4]},
								"down": {"uv": [4, 4], "uv_size": [-4, -4]}
							}
						},
						{
							"origin": [-2, 9, -2],
							"size": [4, 1, 4],
							"uv": {
								"north": {"uv": [0, 0], "uv_size": [4, 2]},
								"east": {"uv": [0, 0], "uv_size": [4, 2]},
								"south": {"uv": [0, 0], "uv_size": [4, 2]},
								"west": {"uv": [0, 0], "uv_size": [4, 2]},
								"up": {"uv": [4, 4], "uv_size": [-4, -4]},
								"down": {"uv": [4, 4], "uv_size": [-4, -4]}
							}
						},
						{
							"origin": [-2.5, 10, -2.5],
							"size": [5, 1.5, 5],
							"uv": {
								"north": {"uv": [0, 0], "uv_size": [4, 2]},
								"east": {"uv": [0, 0], "uv_size": [4, 2]},
								"south": {"uv": [0, 0], "uv_size": [4, 2]},
								"west": {"uv": [0, 0], "uv_size": [4, 2]},
								"up": {"uv": [4, 4], "uv_size": [-4, -4]},
								"down": {"uv": [4, 4], "uv_size": [-4, -4]}
							}
						},
						{
							"origin": [-3, 11.5, -3],
							"size": [6, 2, 6],
							"uv": {
								"north": {"uv": [0, 0], "uv_size": [4, 2]},
								"east": {"uv": [0, 0], "uv_size": [4, 2]},
								"south": {"uv": [0, 0], "uv_size": [4, 2]},
								"west": {"uv": [0, 0], "uv_size": [4, 2]},
								"up": {"uv": [4, 4], "uv_size": [-4, -4]},
								"down": {"uv": [4, 4], "uv_size": [-4, -4]}
							}
						},
						{
							"origin": [-3.5, 13.5, -3.5],
							"size": [7, 2, 7],
							"uv": {
								"north": {"uv": [0, 0], "uv_size": [4, 2]},
								"east": {"uv": [0, 0], "uv_size": [4, 2]},
								"south": {"uv": [0, 0], "uv_size": [4, 2]},
								"west": {"uv": [0, 0], "uv_size": [4, 2]},
								"up": {"uv": [4, 4], "uv_size": [-4, -4]},
								"down": {"uv": [4, 4], "uv_size": [-4, -4]}
							}
						},
						{
							"origin": [-4.5, 15.5, -4.5],
							"size": [9, 3, 9],
							"uv": {
								"north": {"uv": [0, 0], "uv_size": [4, 2]},
								"east": {"uv": [0, 0], "uv_size": [4, 2]},
								"south": {"uv": [0, 0], "uv_size": [4, 2]},
								"west": {"uv": [0, 0], "uv_size": [4, 2]},
								"up": {"uv": [4, 4], "uv_size": [-4, -4]},
								"down": {"uv": [4, 4], "uv_size": [-4, -4]}
							}
						},
						{
							"origin": [-4.5, 15.5, -4.5],
							"size": [9, 3, 9],
							"pivot": [0, 16, 0],
							"rotation": [0, -45, 0],
							"uv": {
								"north": {"uv": [0, 0], "uv_size": [4, 2]},
								"east": {"uv": [0, 0], "uv_size": [4, 2]},
								"south": {"uv": [0, 0], "uv_size": [4, 2]},
								"west": {"uv": [0, 0], "uv_size": [4, 2]},
								"up": {"uv": [4, 4], "uv_size": [-4, -4]},
								"down": {"uv": [4, 4], "uv_size": [-4, -4]}
							}
						},
						{
							"origin": [-3.5, 13.5, -3.5],
							"size": [7, 2, 7],
							"pivot": [0, 14, 0],
							"rotation": [0, -45, 0],
							"uv": {
								"north": {"uv": [0, 0], "uv_size": [4, 2]},
								"east": {"uv": [0, 0], "uv_size": [4, 2]},
								"south": {"uv": [0, 0], "uv_size": [4, 2]},
								"west": {"uv": [0, 0], "uv_size": [4, 2]},
								"up": {"uv": [4, 4], "uv_size": [-4, -4]},
								"down": {"uv": [4, 4], "uv_size": [-4, -4]}
							}
						},
						{
							"origin": [-3, 11.5, -3],
							"size": [6, 2, 6],
							"pivot": [0, 12, 0],
							"rotation": [0, -45, 0],
							"uv": {
								"north": {"uv": [0, 0], "uv_size": [4, 2]},
								"east": {"uv": [0, 0], "uv_size": [4, 2]},
								"south": {"uv": [0, 0], "uv_size": [4, 2]},
								"west": {"uv": [0, 0], "uv_size": [4, 2]},
								"up": {"uv": [4, 4], "uv_size": [-4, -4]},
								"down": {"uv": [4, 4], "uv_size": [-4, -4]}
							}
						},
						{
							"origin": [-2.5, 10, -2.5],
							"size": [5, 1.5, 5],
							"pivot": [0, 10.5, 0],
							"rotation": [0, -45, 0],
							"uv": {
								"north": {"uv": [0, 0], "uv_size": [4, 2]},
								"east": {"uv": [0, 0], "uv_size": [4, 2]},
								"south": {"uv": [0, 0], "uv_size": [4, 2]},
								"west": {"uv": [0, 0], "uv_size": [4, 2]},
								"up": {"uv": [4, 4], "uv_size": [-4, -4]},
								"down": {"uv": [4, 4], "uv_size": [-4, -4]}
							}
						}
					]
				},
				{
					"name": "tige",
					"parent": "tige_head",
					"pivot": [0, 8, 0],
					"cubes": [
						{
							"origin": [-2, 18, -2],
							"size": [4, 50, 4],
							"pivot": [0, 18.5, 0],
							"rotation": [0, 22.5, 0],
							"uv": {
								"north": {"uv": [32, 32], "uv_size": [4, 2]},
								"east": {"uv": [32, 32], "uv_size": [4, 2]},
								"south": {"uv": [32, 32], "uv_size": [4, 2]},
								"west": {"uv": [32, 32], "uv_size": [4, 2]},
								"up": {"uv": [36, 36], "uv_size": [-4, -4]},
								"down": {"uv": [36, 36], "uv_size": [-4, -4]}
							}
						},
						{
							"origin": [-2, 18, -2],
							"size": [4, 50, 4],
							"pivot": [0, 18.5, 0],
							"rotation": [0, -45, 0],
							"uv": {
								"north": {"uv": [32, 32], "uv_size": [4, 2]},
								"east": {"uv": [32, 32], "uv_size": [4, 2]},
								"south": {"uv": [32, 32], "uv_size": [4, 2]},
								"west": {"uv": [32, 32], "uv_size": [4, 2]},
								"up": {"uv": [36, 36], "uv_size": [-4, -4]},
								"down": {"uv": [36, 36], "uv_size": [-4, -4]}
							}
						},
						{
							"origin": [-2, 18, -2],
							"size": [4, 50, 4],
							"pivot": [0, 18.5, 0],
							"rotation": [0, -22.5, 0],
							"uv": {
								"north": {"uv": [32, 32], "uv_size": [4, 2]},
								"east": {"uv": [32, 32], "uv_size": [4, 2]},
								"south": {"uv": [32, 32], "uv_size": [4, 2]},
								"west": {"uv": [32, 32], "uv_size": [4, 2]},
								"up": {"uv": [36, 36], "uv_size": [-4, -4]},
								"down": {"uv": [36, 36], "uv_size": [-4, -4]}
							}
						},
						{
							"origin": [-2, 18, -2],
							"size": [4, 50, 4],
							"uv": {
								"north": {"uv": [32, 32], "uv_size": [4, 2]},
								"east": {"uv": [32, 32], "uv_size": [4, 2]},
								"south": {"uv": [32, 32], "uv_size": [4, 2]},
								"west": {"uv": [32, 32], "uv_size": [4, 2]},
								"up": {"uv": [36, 36], "uv_size": [-4, -4]},
								"down": {"uv": [36, 36], "uv_size": [-4, -4]}
							}
						}
					]
				},
				{
					"name": "Caisse",
					"parent": "Miner_MK1",
					"pivot": [0, 12.5, -13],
					"cubes": [
						{
							"origin": [-7, 7.5, -51],
							"size": [14, 14, 28],
							"uv": {
								"north": {"uv": [0, 0], "uv_size": [32, 4]},
								"east": {"uv": [0, 0], "uv_size": [4, 4]},
								"south": {"uv": [0, 0], "uv_size": [32, 4]},
								"west": {"uv": [0, 0], "uv_size": [4, 4]},
								"up": {"uv": [32, 4], "uv_size": [-32, -4]},
								"down": {"uv": [32, 4], "uv_size": [-32, -4]}
							}
						},
						{
							"origin": [-10, 7.5, -51],
							"size": [2, 14, 28],
							"uv": {
								"north": {"uv": [64, 0], "uv_size": [32, 4]},
								"east": {"uv": [64, 14], "uv_size": [32, 18]},
								"south": {"uv": [64, 0], "uv_size": [32, 4]},
								"west": {"uv": [64, 0], "uv_size": [4, 4]},
								"up": {"uv": [96, 4], "uv_size": [-32, -4]},
								"down": {"uv": [96, 4], "uv_size": [-32, -4]}
							}
						},
						{
							"origin": [-7, 4.5, -51],
							"size": [14, 2, 28],
							"uv": {
								"north": {"uv": [64, 0], "uv_size": [32, 4]},
								"east": {"uv": [64, 0], "uv_size": [4, 4]},
								"south": {"uv": [64, 0], "uv_size": [32, 4]},
								"west": {"uv": [64, 0], "uv_size": [4, 4]},
								"up": {"uv": [96, 4], "uv_size": [-32, -4]},
								"down": {"uv": [96, 4], "uv_size": [-32, -4]}
							}
						},
						{
							"origin": [-7, 7.5, -23],
							"size": [14, 14, 3],
							"uv": {
								"north": {"uv": [64, 0], "uv_size": [32, 4]},
								"east": {"uv": [64, 0], "uv_size": [4, 4]},
								"south": {"uv": [64, 0], "uv_size": [32, 4]},
								"west": {"uv": [64, 0], "uv_size": [4, 4]},
								"up": {"uv": [96, 4], "uv_size": [-32, -4]},
								"down": {"uv": [96, 4], "uv_size": [-32, -4]}
							}
						},
						{
							"origin": [-7, 18.65, -25.45],
							"size": [14, 4.5, 4.3],
							"pivot": [0, 20.9, -22.65],
							"rotation": [-45, 0, 0],
							"uv": {
								"north": {"uv": [64, 0], "uv_size": [32, 4]},
								"east": {"uv": [64, 0], "uv_size": [4, 4]},
								"south": {"uv": [64, 0], "uv_size": [32, 4]},
								"west": {"uv": [64, 0], "uv_size": [4, 4]},
								"up": {"uv": [96, 4], "uv_size": [-32, -4]},
								"down": {"uv": [96, 4], "uv_size": [-32, -4]}
							}
						},
						{
							"origin": [-7, 23, -52.05],
							"size": [14, 1.1, 3.1],
							"pivot": [0, 21.85, -50.45],
							"rotation": [45, 0, 0],
							"uv": {
								"north": {"uv": [96, 4], "uv_size": [-32, -4]},
								"east": {"uv": [68, 4], "uv_size": [-4, -4]},
								"south": {"uv": [96, 4], "uv_size": [-32, -4]},
								"west": {"uv": [68, 4], "uv_size": [-4, -4]},
								"up": {"uv": [64, 0], "uv_size": [32, 4]},
								"down": {"uv": [64, 0], "uv_size": [32, 4]}
							}
						},
						{
							"origin": [-7, 22, -52.05],
							"size": [14, 1.1, 3.1],
							"uv": {
								"north": {"uv": [96, 4], "uv_size": [-32, -4]},
								"east": {"uv": [68, 4], "uv_size": [-4, -4]},
								"south": {"uv": [96, 4], "uv_size": [-32, -4]},
								"west": {"uv": [68, 4], "uv_size": [-4, -4]},
								"up": {"uv": [64, 0], "uv_size": [32, 4]},
								"down": {"uv": [64, 0], "uv_size": [32, 4]}
							}
						},
						{
							"origin": [-7, 5.9, -52.05],
							"size": [14, 1.1, 3.1],
							"uv": {
								"north": {"uv": [96, 0], "uv_size": [-32, 4]},
								"east": {"uv": [68, 0], "uv_size": [-4, 4]},
								"south": {"uv": [96, 0], "uv_size": [-32, 4]},
								"west": {"uv": [68, 0], "uv_size": [-4, 4]},
								"up": {"uv": [64, 4], "uv_size": [32, -4]},
								"down": {"uv": [64, 4], "uv_size": [32, -4]}
							}
						},
						{
							"origin": [-7, 4.9, -52.05],
							"size": [14, 1.1, 3.1],
							"pivot": [0, 7.15, -50.45],
							"rotation": [-45, 0, 0],
							"uv": {
								"north": {"uv": [96, 0], "uv_size": [-32, 4]},
								"east": {"uv": [68, 0], "uv_size": [-4, 4]},
								"south": {"uv": [96, 0], "uv_size": [-32, 4]},
								"west": {"uv": [68, 0], "uv_size": [-4, 4]},
								"up": {"uv": [64, 4], "uv_size": [32, -4]},
								"down": {"uv": [64, 4], "uv_size": [32, -4]}
							}
						},
						{
							"origin": [-7, 5.85, -25.45],
							"size": [14, 4.5, 4.3],
							"pivot": [0, 8.1, -22.65],
							"rotation": [45, 0, 0],
							"uv": {
								"north": {"uv": [64, 4], "uv_size": [32, -4]},
								"east": {"uv": [64, 4], "uv_size": [4, -4]},
								"south": {"uv": [64, 4], "uv_size": [32, -4]},
								"west": {"uv": [64, 4], "uv_size": [4, -4]},
								"up": {"uv": [96, 0], "uv_size": [-32, 4]},
								"down": {"uv": [96, 0], "uv_size": [-32, 4]}
							}
						},
						{
							"origin": [-9.6, 7.5, -24],
							"size": [4.25, 14, 3],
							"pivot": [-7.35, 14.5, -22.5],
							"rotation": [0, -45, 0],
							"uv": {
								"north": {"uv": [64, 0], "uv_size": [32, 4]},
								"east": {"uv": [64, 0], "uv_size": [4, 4]},
								"south": {"uv": [64, 0], "uv_size": [32, 4]},
								"west": {"uv": [64, 0], "uv_size": [4, 4]},
								"up": {"uv": [96, 4], "uv_size": [-32, -4]},
								"down": {"uv": [96, 4], "uv_size": [-32, -4]}
							}
						},
						{
							"origin": [-9.6, 7.5, -52],
							"size": [1.25, 14, 3],
							"pivot": [-7.35, 14.5, -50.5],
							"rotation": [0, -45, 0],
							"uv": {
								"north": {"uv": [64, 0], "uv_size": [32, 4]},
								"east": {"uv": [64, 0], "uv_size": [4, 4]},
								"south": {"uv": [64, 0], "uv_size": [32, 4]},
								"west": {"uv": [64, 0], "uv_size": [4, 4]},
								"up": {"uv": [96, 4], "uv_size": [-32, -4]},
								"down": {"uv": [96, 4], "uv_size": [-32, -4]}
							}
						},
						{
							"origin": [-8.6, 7.5, -52],
							"size": [1.25, 14, 3],
							"uv": {
								"north": {"uv": [64, 0], "uv_size": [32, 4]},
								"east": {"uv": [64, 0], "uv_size": [4, 4]},
								"south": {"uv": [64, 0], "uv_size": [32, 4]},
								"west": {"uv": [64, 0], "uv_size": [4, 4]},
								"up": {"uv": [96, 4], "uv_size": [-32, -4]},
								"down": {"uv": [96, 4], "uv_size": [-32, -4]}
							}
						},
						{
							"origin": [7.35, 7.5, -52],
							"size": [1.25, 14, 3],
							"uv": {
								"north": {"uv": [96, 0], "uv_size": [-32, 4]},
								"east": {"uv": [68, 0], "uv_size": [-4, 4]},
								"south": {"uv": [96, 0], "uv_size": [-32, 4]},
								"west": {"uv": [68, 0], "uv_size": [-4, 4]},
								"up": {"uv": [64, 4], "uv_size": [32, -4]},
								"down": {"uv": [64, 4], "uv_size": [32, -4]}
							}
						},
						{
							"origin": [8.35, 7.5, -52],
							"size": [1.25, 14, 3],
							"pivot": [7.35, 14.5, -50.5],
							"rotation": [0, 45, 0],
							"uv": {
								"north": {"uv": [96, 0], "uv_size": [-32, 4]},
								"east": {"uv": [68, 0], "uv_size": [-4, 4]},
								"south": {"uv": [96, 0], "uv_size": [-32, 4]},
								"west": {"uv": [68, 0], "uv_size": [-4, 4]},
								"up": {"uv": [64, 4], "uv_size": [32, -4]},
								"down": {"uv": [64, 4], "uv_size": [32, -4]}
							}
						},
						{
							"origin": [5.35, 7.5, -24],
							"size": [4.25, 14, 3],
							"pivot": [7.35, 14.5, -22.5],
							"rotation": [0, 45, 0],
							"uv": {
								"north": {"uv": [96, 0], "uv_size": [-32, 4]},
								"east": {"uv": [68, 0], "uv_size": [-4, 4]},
								"south": {"uv": [96, 0], "uv_size": [-32, 4]},
								"west": {"uv": [68, 0], "uv_size": [-4, 4]},
								"up": {"uv": [64, 4], "uv_size": [32, -4]},
								"down": {"uv": [64, 4], "uv_size": [32, -4]}
							}
						},
						{
							"origin": [-7, 22.5, -51],
							"size": [14, 2, 28],
							"uv": {
								"north": {"uv": [64, 0], "uv_size": [32, 4]},
								"east": {"uv": [64, 0], "uv_size": [4, 4]},
								"south": {"uv": [64, 0], "uv_size": [32, 4]},
								"west": {"uv": [64, 0], "uv_size": [4, 4]},
								"up": {"uv": [96, 32], "uv_size": [-32, -4]},
								"down": {"uv": [96, 4], "uv_size": [-32, -4]}
							}
						},
						{
							"origin": [5.15, 21, -51],
							"size": [4.25, 2, 28],
							"pivot": [7.9, 21.5, -38],
							"rotation": [0, 0, 45],
							"uv": {
								"north": {"uv": [96, 0], "uv_size": [-32, 4]},
								"east": {"uv": [68, 0], "uv_size": [-4, 4]},
								"south": {"uv": [96, 0], "uv_size": [-32, 4]},
								"west": {"uv": [68, 0], "uv_size": [-4, 4]},
								"up": {"uv": [64, 4], "uv_size": [32, -4]},
								"down": {"uv": [64, 4], "uv_size": [32, -4]}
							}
						},
						{
							"origin": [5.15, 6, -51],
							"size": [4.25, 2, 28],
							"pivot": [7.9, 7.5, -38],
							"rotation": [0, 0, -45],
							"uv": {
								"north": {"uv": [96, 4], "uv_size": [-32, -4]},
								"east": {"uv": [68, 4], "uv_size": [-4, -4]},
								"south": {"uv": [96, 4], "uv_size": [-32, -4]},
								"west": {"uv": [68, 4], "uv_size": [-4, -4]},
								"up": {"uv": [64, 0], "uv_size": [32, 4]},
								"down": {"uv": [64, 0], "uv_size": [32, 4]}
							}
						},
						{
							"origin": [-9.4, 6, -51],
							"size": [4.25, 2, 28],
							"pivot": [-7.9, 7.5, -38],
							"rotation": [0, 0, 45],
							"uv": {
								"north": {"uv": [64, 4], "uv_size": [32, -4]},
								"east": {"uv": [64, 4], "uv_size": [4, -4]},
								"south": {"uv": [64, 4], "uv_size": [32, -4]},
								"west": {"uv": [64, 4], "uv_size": [4, -4]},
								"up": {"uv": [96, 0], "uv_size": [-32, 4]},
								"down": {"uv": [96, 0], "uv_size": [-32, 4]}
							}
						},
						{
							"origin": [-9.4, 21, -51],
							"size": [4.25, 2, 28],
							"pivot": [-7.9, 21.5, -38],
							"rotation": [0, 0, -45],
							"uv": {
								"north": {"uv": [64, 0], "uv_size": [32, 4]},
								"east": {"uv": [64, 0], "uv_size": [4, 4]},
								"south": {"uv": [64, 0], "uv_size": [32, 4]},
								"west": {"uv": [64, 0], "uv_size": [4, 4]},
								"up": {"uv": [96, 4], "uv_size": [-32, -4]},
								"down": {"uv": [96, 4], "uv_size": [-32, -4]}
							}
						},
						{
							"origin": [8, 7.5, -51],
							"size": [2, 14, 28],
							"uv": {
								"north": {"uv": [96, 0], "uv_size": [-32, 4]},
								"east": {"uv": [68, 0], "uv_size": [-4, 4]},
								"south": {"uv": [96, 0], "uv_size": [-32, 4]},
								"west": {"uv": [96, 14], "uv_size": [-32, 18]},
								"up": {"uv": [64, 4], "uv_size": [32, -4]},
								"down": {"uv": [64, 4], "uv_size": [32, -4]}
							}
						},
						{
							"origin": [-3, 21, -23],
							"size": [6, 6, 21],
							"pivot": [0, 24, -12.5],
							"rotation": [22.5, 0, 0],
							"uv": {
								"north": {"uv": [32, 32], "uv_size": [32, 4]},
								"east": {"uv": [32, 32], "uv_size": [4, 4]},
								"south": {"uv": [32, 32], "uv_size": [32, 4]},
								"west": {"uv": [32, 32], "uv_size": [4, 4]},
								"up": {"uv": [64, 36], "uv_size": [-32, -4]},
								"down": {"uv": [64, 36], "uv_size": [-32, -4]}
							}
						}
					]
				},
				{
					"name": "group",
					"parent": "Caisse",
					"pivot": [-7.9, 7.5, -40],
					"cubes": [
						{
							"origin": [-7, 6.5, -55],
							"size": [14, 1, 4],
							"uv": {
								"north": {"uv": [32, 0], "uv_size": [32, 4]},
								"east": {"uv": [32, 0], "uv_size": [4, 4]},
								"south": {"uv": [32, 0], "uv_size": [32, 4]},
								"west": {"uv": [32, 0], "uv_size": [4, 4]},
								"up": {"uv": [64, 4], "uv_size": [-32, -4]},
								"down": {"uv": [64, 4], "uv_size": [-32, -4]}
							}
						},
						{
							"origin": [6.4, 7.5, -55],
							"size": [1.75, 1.5, 4],
							"pivot": [7.9, 7.5, -40],
							"rotation": [0, 0, -45],
							"uv": {
								"north": {"uv": [64, 4], "uv_size": [-32, -4]},
								"east": {"uv": [36, 4], "uv_size": [-4, -4]},
								"south": {"uv": [64, 4], "uv_size": [-32, -4]},
								"west": {"uv": [36, 4], "uv_size": [-4, -4]},
								"up": {"uv": [32, 0], "uv_size": [32, 4]},
								"down": {"uv": [32, 0], "uv_size": [32, 4]}
							}
						},
						{
							"origin": [7, 7.5, -55],
							"size": [1, 14, 4],
							"uv": {
								"north": {"uv": [32, 0], "uv_size": [32, 4]},
								"east": {"uv": [32, 0], "uv_size": [4, 4]},
								"south": {"uv": [32, 0], "uv_size": [32, 4]},
								"west": {"uv": [32, 0], "uv_size": [4, 4]},
								"up": {"uv": [64, 4], "uv_size": [-32, -4]},
								"down": {"uv": [64, 4], "uv_size": [-32, -4]}
							}
						},
						{
							"origin": [6.4, 20, -55],
							"size": [1.75, 1.5, 4],
							"pivot": [7.9, 21.5, -40],
							"rotation": [0, 0, 45],
							"uv": {
								"north": {"uv": [64, 0], "uv_size": [-32, 4]},
								"east": {"uv": [36, 0], "uv_size": [-4, 4]},
								"south": {"uv": [64, 0], "uv_size": [-32, 4]},
								"west": {"uv": [36, 0], "uv_size": [-4, 4]},
								"up": {"uv": [32, 4], "uv_size": [32, -4]},
								"down": {"uv": [32, 4], "uv_size": [32, -4]}
							}
						},
						{
							"origin": [-7, 21.5, -55],
							"size": [14, 1, 4],
							"uv": {
								"north": {"uv": [32, 0], "uv_size": [32, 4]},
								"east": {"uv": [32, 0], "uv_size": [4, 4]},
								"south": {"uv": [32, 0], "uv_size": [32, 4]},
								"west": {"uv": [32, 0], "uv_size": [4, 4]},
								"up": {"uv": [64, 4], "uv_size": [-32, -4]},
								"down": {"uv": [64, 4], "uv_size": [-32, -4]}
							}
						},
						{
							"origin": [-8.15, 20, -55],
							"size": [1.75, 1.5, 4],
							"pivot": [-7.9, 21.5, -40],
							"rotation": [0, 0, -45],
							"uv": {
								"north": {"uv": [32, 0], "uv_size": [32, 4]},
								"east": {"uv": [32, 0], "uv_size": [4, 4]},
								"south": {"uv": [32, 0], "uv_size": [32, 4]},
								"west": {"uv": [32, 0], "uv_size": [4, 4]},
								"up": {"uv": [64, 4], "uv_size": [-32, -4]},
								"down": {"uv": [64, 4], "uv_size": [-32, -4]}
							}
						},
						{
							"origin": [-8, 7.5, -55],
							"size": [1, 14, 4],
							"uv": {
								"north": {"uv": [32, 0], "uv_size": [32, 4]},
								"east": {"uv": [32, 0], "uv_size": [4, 4]},
								"south": {"uv": [32, 0], "uv_size": [32, 4]},
								"west": {"uv": [32, 0], "uv_size": [4, 4]},
								"up": {"uv": [64, 4], "uv_size": [-32, -4]},
								"down": {"uv": [64, 4], "uv_size": [-32, -4]}
							}
						},
						{
							"origin": [-8.15, 7.5, -55],
							"size": [1.75, 1.5, 4],
							"pivot": [-7.9, 7.5, -40],
							"rotation": [0, 0, 45],
							"uv": {
								"north": {"uv": [32, 4], "uv_size": [32, -4]},
								"east": {"uv": [32, 4], "uv_size": [4, -4]},
								"south": {"uv": [32, 4], "uv_size": [32, -4]},
								"west": {"uv": [32, 4], "uv_size": [4, -4]},
								"up": {"uv": [64, 0], "uv_size": [-32, 4]},
								"down": {"uv": [64, 0], "uv_size": [-32, 4]}
							}
						}
					]
				},
				{
					"name": "chassis",
					"parent": "Miner_MK1",
					"pivot": [13.98691, 0.50002, -14.01311],
					"cubes": [
						{
							"origin": [-15, 35, -15],
							"size": [30, 7, 1],
							"uv": {
								"north": {"uv": [64, 0], "uv_size": [-32, 14]},
								"east": {"uv": [34, 0], "uv_size": [-2, 14]},
								"south": {"uv": [64, 0], "uv_size": [-32, 14]},
								"west": {"uv": [34, 0], "uv_size": [-2, 14]},
								"up": {"uv": [64, 0], "uv_size": [-32, 2]},
								"down": {"uv": [64, 0], "uv_size": [-32, 2]}
							}
						},
						{
							"origin": [-15, 35, 14],
							"size": [30, 7, 1],
							"uv": {
								"north": {"uv": [32, 0], "uv_size": [32, 14]},
								"east": {"uv": [32, 0], "uv_size": [2, 14]},
								"south": {"uv": [32, 0], "uv_size": [32, 14]},
								"west": {"uv": [32, 0], "uv_size": [2, 14]},
								"up": {"uv": [64, 2], "uv_size": [-32, -2]},
								"down": {"uv": [64, 2], "uv_size": [-32, -2]}
							}
						},
						{
							"origin": [-15, 35, -14],
							"size": [1, 7, 28],
							"uv": {
								"north": {"uv": [50, 0], "uv_size": [-2, 14]},
								"east": {"uv": [64, 0], "uv_size": [-32, 14]},
								"south": {"uv": [50, 0], "uv_size": [-2, 14]},
								"west": {"uv": [64, 0], "uv_size": [-32, 14]},
								"up": {"uv": [48, 32], "uv_size": [2, -32]},
								"down": {"uv": [48, 32], "uv_size": [2, -32]}
							}
						},
						{
							"origin": [14, 35, -14],
							"size": [1, 7, 28],
							"uv": {
								"north": {"uv": [48, 0], "uv_size": [2, 14]},
								"east": {"uv": [32, 0], "uv_size": [32, 14]},
								"south": {"uv": [48, 0], "uv_size": [2, 14]},
								"west": {"uv": [32, 0], "uv_size": [32, 14]},
								"up": {"uv": [50, 32], "uv_size": [-2, -32]},
								"down": {"uv": [50, 32], "uv_size": [-2, -32]}
							}
						},
						{
							"origin": [6, 39, -14],
							"size": [8, 3, 28],
							"uv": {
								"north": {"uv": [48, 0], "uv_size": [-16, 6]},
								"east": {"uv": [64, 0], "uv_size": [-32, 6]},
								"south": {"uv": [48, 0], "uv_size": [-16, 6]},
								"west": {"uv": [64, 0], "uv_size": [-32, 6]},
								"up": {"uv": [32, 32], "uv_size": [16, -32]},
								"down": {"uv": [32, 32], "uv_size": [16, -32]}
							}
						},
						{
							"origin": [-14, 39, -14],
							"size": [8, 3, 28],
							"uv": {
								"north": {"uv": [32, 0], "uv_size": [16, 6]},
								"east": {"uv": [32, 0], "uv_size": [32, 6]},
								"south": {"uv": [32, 0], "uv_size": [16, 6]},
								"west": {"uv": [32, 0], "uv_size": [32, 6]},
								"up": {"uv": [48, 32], "uv_size": [-16, -32]},
								"down": {"uv": [48, 32], "uv_size": [-16, -32]}
							}
						},
						{
							"origin": [-14, 39, 6],
							"size": [28, 3, 8],
							"uv": {
								"north": {"uv": [64, 0], "uv_size": [-32, 6]},
								"east": {"uv": [48, 0], "uv_size": [-16, 6]},
								"south": {"uv": [64, 0], "uv_size": [-32, 6]},
								"west": {"uv": [48, 0], "uv_size": [-16, 6]},
								"up": {"uv": [64, 0], "uv_size": [-32, 16]},
								"down": {"uv": [64, 0], "uv_size": [-32, 16]}
							}
						},
						{
							"origin": [-15, 39, -39],
							"size": [30, 3, 33],
							"uv": {
								"north": {"uv": [32, 0], "uv_size": [32, 6]},
								"east": {"uv": [32, 0], "uv_size": [16, 6]},
								"south": {"uv": [32, 0], "uv_size": [32, 6]},
								"west": {"uv": [32, 0], "uv_size": [16, 6]},
								"up": {"uv": [64, 16], "uv_size": [-32, -16]},
								"down": {"uv": [64, 16], "uv_size": [-32, -16]}
							}
						},
						{
							"origin": [-14, 2, -14],
							"size": [4, 40, 4],
							"uv": {
								"north": {"uv": [32, 0], "uv_size": [8, 32]},
								"east": {"uv": [32, 0], "uv_size": [8, 32]},
								"south": {"uv": [32, 0], "uv_size": [8, 32]},
								"west": {"uv": [32, 0], "uv_size": [8, 32]},
								"up": {"uv": [40, 8], "uv_size": [-8, -8]},
								"down": {"uv": [40, 8], "uv_size": [-8, -8]}
							}
						},
						{
							"origin": [-9, 82, -8],
							"size": [17, 4, 16],
							"uv": {
								"north": {"uv": [64, 0], "uv_size": [30, 8]},
								"east": {"uv": [64, 0], "uv_size": [32, 8]},
								"south": {"uv": [64, 0], "uv_size": [30, 8]},
								"west": {"uv": [64, 0], "uv_size": [32, 8]},
								"up": {"uv": [94, 32], "uv_size": [-30, -32]},
								"down": {"uv": [94, 32], "uv_size": [-30, -32]}
							}
						},
						{
							"origin": [-14, 2, 10],
							"size": [4, 40, 4],
							"uv": {
								"north": {"uv": [32, 0], "uv_size": [8, 32]},
								"east": {"uv": [32, 0], "uv_size": [8, 32]},
								"south": {"uv": [32, 0], "uv_size": [8, 32]},
								"west": {"uv": [32, 0], "uv_size": [8, 32]},
								"up": {"uv": [40, 8], "uv_size": [-8, -8]},
								"down": {"uv": [40, 8], "uv_size": [-8, -8]}
							}
						},
						{
							"origin": [-15, 82, 8],
							"size": [30, 4, 7],
							"uv": {
								"north": {"uv": [64, 0], "uv_size": [32, 8]},
								"east": {"uv": [64, 0], "uv_size": [14, 8]},
								"south": {"uv": [64, 0], "uv_size": [32, 8]},
								"west": {"uv": [64, 0], "uv_size": [14, 8]},
								"up": {"uv": [96, 14], "uv_size": [-32, -14]},
								"down": {"uv": [96, 14], "uv_size": [-32, -14]}
							}
						},
						{
							"origin": [-8, 42, -7],
							"size": [15, 42, 15],
							"uv": {
								"north": {"uv": [34, 0], "uv_size": [30, 32]},
								"east": {"uv": [34, 0], "uv_size": [30, 32]},
								"south": {"uv": [34, 0], "uv_size": [30, 32]},
								"west": {"uv": [34, 0], "uv_size": [30, 32]},
								"up": {"uv": [64, 30], "uv_size": [-30, -30]},
								"down": {"uv": [64, 30], "uv_size": [-30, -30]}
							}
						},
						{
							"origin": [-9, 41, -8],
							"size": [17, 10, 17],
							"uv": {
								"north": {"uv": [66, 0], "uv_size": [30, 32]},
								"east": {"uv": [66, 0], "uv_size": [30, 32]},
								"south": {"uv": [66, 0], "uv_size": [30, 32]},
								"west": {"uv": [66, 0], "uv_size": [30, 32]},
								"up": {"uv": [96, 30], "uv_size": [-30, -30]},
								"down": {"uv": [96, 30], "uv_size": [-30, -30]}
							}
						},
						{
							"origin": [-14, 42, 11],
							"size": [4, 42, 2],
							"uv": {
								"north": {"uv": [40, 0], "uv_size": [8, 32]},
								"east": {"uv": [36, 0], "uv_size": [4, 32]},
								"south": {"uv": [40, 0], "uv_size": [8, 32]},
								"west": {"uv": [36, 0], "uv_size": [4, 32]},
								"up": {"uv": [48, 4], "uv_size": [-8, -4]},
								"down": {"uv": [48, 4], "uv_size": [-8, -4]}
							}
						},
						{
							"origin": [10, 42, 11],
							"size": [4, 42, 2],
							"uv": {
								"north": {"uv": [32, 0], "uv_size": [8, 32]},
								"east": {"uv": [32, 0], "uv_size": [4, 32]},
								"south": {"uv": [32, 0], "uv_size": [8, 32]},
								"west": {"uv": [32, 0], "uv_size": [4, 32]},
								"up": {"uv": [40, 4], "uv_size": [-8, -4]},
								"down": {"uv": [40, 4], "uv_size": [-8, -4]}
							}
						},
						{
							"origin": [10, 2, 10],
							"size": [4, 40, 4],
							"uv": {
								"north": {"uv": [32, 0], "uv_size": [8, 32]},
								"east": {"uv": [32, 0], "uv_size": [8, 32]},
								"south": {"uv": [32, 0], "uv_size": [8, 32]},
								"west": {"uv": [32, 0], "uv_size": [8, 32]},
								"up": {"uv": [40, 8], "uv_size": [-8, -8]},
								"down": {"uv": [40, 8], "uv_size": [-8, -8]}
							}
						},
						{
							"origin": [10, 2, -14],
							"size": [4, 40, 4],
							"uv": {
								"north": {"uv": [32, 0], "uv_size": [8, 32]},
								"east": {"uv": [32, 0], "uv_size": [8, 32]},
								"south": {"uv": [32, 0], "uv_size": [8, 32]},
								"west": {"uv": [32, 0], "uv_size": [8, 32]},
								"up": {"uv": [40, 8], "uv_size": [-8, -8]},
								"down": {"uv": [40, 8], "uv_size": [-8, -8]}
							}
						},
						{
							"origin": [6, 83, -3],
							"size": [4, 25, 4],
							"uv": {
								"north": {"uv": [65, 32], "uv_size": [2, 32]},
								"east": {"uv": [65, 32], "uv_size": [2, 32]},
								"south": {"uv": [65, 32], "uv_size": [2, 32]},
								"west": {"uv": [65, 32], "uv_size": [2, 32]},
								"up": {"uv": [67, 35], "uv_size": [-2, -2]},
								"down": {"uv": [67, 35], "uv_size": [-2, -2]}
							}
						}
					]
				},
				{
					"name": "contour",
					"parent": "Miner_MK1",
					"pivot": [0, 8, 0],
					"cubes": [
						{
							"origin": [-14, 0, -14],
							"size": [28, 2, 5],
							"uv": {
								"north": {"uv": [32, 32], "uv_size": [32, 4]},
								"east": {"uv": [32, 32], "uv_size": [10, 4]},
								"south": {"uv": [32, 32], "uv_size": [32, 4]},
								"west": {"uv": [32, 32], "uv_size": [10, 4]},
								"up": {"uv": [64, 42], "uv_size": [-32, -10]},
								"down": {"uv": [64, 42], "uv_size": [-32, -10]}
							}
						},
						{
							"origin": [-14, 1.3, -9.8],
							"size": [5, 2, 7],
							"pivot": [-11.52527, 2.21053, -6.16422],
							"rotation": [22.5, 0, 0],
							"uv": {
								"north": {"uv": [42, 32], "uv_size": [10, 4]},
								"east": {"uv": [46, 32], "uv_size": [14, 4]},
								"south": {"uv": [42, 32], "uv_size": [10, 4]},
								"west": {"uv": [46, 32], "uv_size": [14, 4]},
								"up": {"uv": [42, 60], "uv_size": [-10, -14]},
								"down": {"uv": [42, 60], "uv_size": [-10, -14]}
							}
						},
						{
							"origin": [-14, 1.3, -35.8],
							"size": [5, 2, 7],
							"pivot": [-11.52527, 2.21053, -32.16422],
							"rotation": [22.5, 0, 0],
							"uv": {
								"north": {"uv": [42, 32], "uv_size": [10, 4]},
								"east": {"uv": [46, 32], "uv_size": [14, 4]},
								"south": {"uv": [42, 32], "uv_size": [10, 4]},
								"west": {"uv": [46, 32], "uv_size": [14, 4]},
								"up": {"uv": [42, 60], "uv_size": [-10, -14]},
								"down": {"uv": [42, 60], "uv_size": [-10, -14]}
							}
						},
						{
							"origin": [-13, 1.25, -47.8],
							"size": [7, 2, 3],
							"pivot": [-9.5, 2.25, -44.3],
							"rotation": [0, 0, -22.5],
							"uv": {
								"north": {"uv": [42, 32], "uv_size": [10, 4]},
								"east": {"uv": [46, 32], "uv_size": [14, 4]},
								"south": {"uv": [42, 32], "uv_size": [10, 4]},
								"west": {"uv": [46, 32], "uv_size": [14, 4]},
								"up": {"uv": [42, 60], "uv_size": [-10, -14]},
								"down": {"uv": [42, 60], "uv_size": [-10, -14]}
							}
						},
						{
							"origin": [-13, 1.25, -38.8],
							"size": [7, 2, 3],
							"pivot": [-9.5, 2.25, -35.3],
							"rotation": [0, 0, -22.5],
							"uv": {
								"north": {"uv": [42, 32], "uv_size": [10, 4]},
								"east": {"uv": [46, 32], "uv_size": [14, 4]},
								"south": {"uv": [42, 32], "uv_size": [10, 4]},
								"west": {"uv": [46, 32], "uv_size": [14, 4]},
								"up": {"uv": [42, 60], "uv_size": [-10, -14]},
								"down": {"uv": [42, 60], "uv_size": [-10, -14]}
							}
						},
						{
							"origin": [6, 1.25, -47.8],
							"size": [7, 2, 3],
							"pivot": [9.5, 2.25, -44.3],
							"rotation": [0, 0, 22.5],
							"uv": {
								"north": {"uv": [52, 32], "uv_size": [-10, 4]},
								"east": {"uv": [60, 32], "uv_size": [-14, 4]},
								"south": {"uv": [52, 32], "uv_size": [-10, 4]},
								"west": {"uv": [60, 32], "uv_size": [-14, 4]},
								"up": {"uv": [32, 60], "uv_size": [10, -14]},
								"down": {"uv": [32, 60], "uv_size": [10, -14]}
							}
						},
						{
							"origin": [6, 1.25, -38.8],
							"size": [7, 2, 3],
							"pivot": [9.5, 2.25, -35.3],
							"rotation": [0, 0, 22.5],
							"uv": {
								"north": {"uv": [52, 32], "uv_size": [-10, 4]},
								"east": {"uv": [60, 32], "uv_size": [-14, 4]},
								"south": {"uv": [52, 32], "uv_size": [-10, 4]},
								"west": {"uv": [60, 32], "uv_size": [-14, 4]},
								"up": {"uv": [32, 60], "uv_size": [10, -14]},
								"down": {"uv": [32, 60], "uv_size": [10, -14]}
							}
						},
						{
							"origin": [9, 1.3, -9.8],
							"size": [5, 2, 7],
							"pivot": [11.52527, 2.21053, -6.16422],
							"rotation": [22.5, 0, 0],
							"uv": {
								"north": {"uv": [32, 32], "uv_size": [10, 4]},
								"east": {"uv": [32, 32], "uv_size": [14, 4]},
								"south": {"uv": [32, 32], "uv_size": [10, 4]},
								"west": {"uv": [32, 32], "uv_size": [14, 4]},
								"up": {"uv": [52, 60], "uv_size": [-10, -14]},
								"down": {"uv": [52, 60], "uv_size": [-10, -14]}
							}
						},
						{
							"origin": [9, 1.3, -35.8],
							"size": [5, 2, 7],
							"pivot": [11.52527, 2.21053, -32.16422],
							"rotation": [22.5, 0, 0],
							"uv": {
								"north": {"uv": [32, 32], "uv_size": [10, 4]},
								"east": {"uv": [32, 32], "uv_size": [14, 4]},
								"south": {"uv": [32, 32], "uv_size": [10, 4]},
								"west": {"uv": [32, 32], "uv_size": [14, 4]},
								"up": {"uv": [52, 60], "uv_size": [-10, -14]},
								"down": {"uv": [52, 60], "uv_size": [-10, -14]}
							}
						},
						{
							"origin": [-14, 1.3, 2.8],
							"size": [5, 2, 7],
							"pivot": [-11.52527, 2.21053, 6.16422],
							"rotation": [-22.5, 0, 0],
							"uv": {
								"north": {"uv": [32, 32], "uv_size": [10, 4]},
								"east": {"uv": [32, 32], "uv_size": [14, 4]},
								"south": {"uv": [32, 32], "uv_size": [10, 4]},
								"west": {"uv": [32, 32], "uv_size": [14, 4]},
								"up": {"uv": [42, 46], "uv_size": [-10, -14]},
								"down": {"uv": [42, 46], "uv_size": [-10, -14]}
							}
						},
						{
							"origin": [-14, 1.3, -23.2],
							"size": [5, 2, 7],
							"pivot": [-11.52527, 2.21053, -19.83578],
							"rotation": [-22.5, 0, 0],
							"uv": {
								"north": {"uv": [32, 32], "uv_size": [10, 4]},
								"east": {"uv": [32, 32], "uv_size": [14, 4]},
								"south": {"uv": [32, 32], "uv_size": [10, 4]},
								"west": {"uv": [32, 32], "uv_size": [14, 4]},
								"up": {"uv": [42, 46], "uv_size": [-10, -14]},
								"down": {"uv": [42, 46], "uv_size": [-10, -14]}
							}
						},
						{
							"origin": [9, 1.3, 2.8],
							"size": [5, 2, 7],
							"pivot": [11.52527, 2.21053, 6.16422],
							"rotation": [-22.5, 0, 0],
							"uv": {
								"north": {"uv": [42, 32], "uv_size": [10, 4]},
								"east": {"uv": [46, 32], "uv_size": [14, 4]},
								"south": {"uv": [42, 32], "uv_size": [10, 4]},
								"west": {"uv": [46, 32], "uv_size": [14, 4]},
								"up": {"uv": [52, 46], "uv_size": [-10, -14]},
								"down": {"uv": [52, 46], "uv_size": [-10, -14]}
							}
						},
						{
							"origin": [9, 1.3, -23.2],
							"size": [5, 2, 7],
							"pivot": [11.52527, 2.21053, -19.83578],
							"rotation": [-22.5, 0, 0],
							"uv": {
								"north": {"uv": [42, 32], "uv_size": [10, 4]},
								"east": {"uv": [46, 32], "uv_size": [14, 4]},
								"south": {"uv": [42, 32], "uv_size": [10, 4]},
								"west": {"uv": [46, 32], "uv_size": [14, 4]},
								"up": {"uv": [52, 46], "uv_size": [-10, -14]},
								"down": {"uv": [52, 46], "uv_size": [-10, -14]}
							}
						},
						{
							"origin": [-14, 2.5, -3.5],
							"size": [5, 2, 7],
							"uv": {
								"north": {"uv": [32, 32], "uv_size": [10, 4]},
								"east": {"uv": [32, 32], "uv_size": [14, 4]},
								"south": {"uv": [32, 32], "uv_size": [10, 4]},
								"west": {"uv": [32, 32], "uv_size": [14, 4]},
								"up": {"uv": [42, 46], "uv_size": [-10, -14]},
								"down": {"uv": [42, 46], "uv_size": [-10, -14]}
							}
						},
						{
							"origin": [-14, 2.5, -29.5],
							"size": [5, 2, 7],
							"uv": {
								"north": {"uv": [32, 32], "uv_size": [10, 4]},
								"east": {"uv": [32, 32], "uv_size": [14, 4]},
								"south": {"uv": [32, 32], "uv_size": [10, 4]},
								"west": {"uv": [32, 32], "uv_size": [14, 4]},
								"up": {"uv": [42, 46], "uv_size": [-10, -14]},
								"down": {"uv": [42, 46], "uv_size": [-10, -14]}
							}
						},
						{
							"origin": [9, 2.5, -3.5],
							"size": [5, 2, 7],
							"uv": {
								"north": {"uv": [42, 32], "uv_size": [10, 4]},
								"east": {"uv": [46, 32], "uv_size": [14, 4]},
								"south": {"uv": [42, 32], "uv_size": [10, 4]},
								"west": {"uv": [46, 32], "uv_size": [14, 4]},
								"up": {"uv": [52, 46], "uv_size": [-10, -14]},
								"down": {"uv": [52, 46], "uv_size": [-10, -14]}
							}
						},
						{
							"origin": [9, 2.5, -29.5],
							"size": [5, 2, 7],
							"uv": {
								"north": {"uv": [42, 32], "uv_size": [10, 4]},
								"east": {"uv": [46, 32], "uv_size": [14, 4]},
								"south": {"uv": [42, 32], "uv_size": [10, 4]},
								"west": {"uv": [46, 32], "uv_size": [14, 4]},
								"up": {"uv": [52, 46], "uv_size": [-10, -14]},
								"down": {"uv": [52, 46], "uv_size": [-10, -14]}
							}
						},
						{
							"origin": [-14, 0, 9],
							"size": [28, 2, 5],
							"uv": {
								"north": {"uv": [32, 32], "uv_size": [32, 4]},
								"east": {"uv": [32, 32], "uv_size": [10, 4]},
								"south": {"uv": [32, 32], "uv_size": [32, 4]},
								"west": {"uv": [32, 32], "uv_size": [10, 4]},
								"up": {"uv": [64, 42], "uv_size": [-32, -10]},
								"down": {"uv": [64, 42], "uv_size": [-32, -10]}
							}
						},
						{
							"origin": [-1, 0, 8],
							"size": [2, 1, 1],
							"uv": {
								"north": {"uv": [36, 32], "uv_size": [-4, 2]},
								"east": {"uv": [34, 32], "uv_size": [-2, 2]},
								"south": {"uv": [36, 32], "uv_size": [-4, 2]},
								"west": {"uv": [34, 32], "uv_size": [-2, 2]},
								"up": {"uv": [36, 32], "uv_size": [-4, 2]},
								"down": {"uv": [36, 32], "uv_size": [-4, 2]}
							}
						},
						{
							"origin": [-9, 3, -1],
							"size": [1, 1, 2],
							"uv": {
								"north": {"uv": [32, 32], "uv_size": [2, 2]},
								"east": {"uv": [32, 32], "uv_size": [4, 2]},
								"south": {"uv": [32, 32], "uv_size": [2, 2]},
								"west": {"uv": [32, 32], "uv_size": [4, 2]},
								"up": {"uv": [34, 36], "uv_size": [-2, -4]},
								"down": {"uv": [34, 36], "uv_size": [-2, -4]}
							}
						},
						{
							"origin": [8, 3, -1],
							"size": [1, 1, 2],
							"uv": {
								"north": {"uv": [34, 32], "uv_size": [-2, 2]},
								"east": {"uv": [36, 32], "uv_size": [-4, 2]},
								"south": {"uv": [34, 32], "uv_size": [-2, 2]},
								"west": {"uv": [36, 32], "uv_size": [-4, 2]},
								"up": {"uv": [32, 36], "uv_size": [2, -4]},
								"down": {"uv": [32, 36], "uv_size": [2, -4]}
							}
						},
						{
							"origin": [-1, 0, -9],
							"size": [2, 1, 1],
							"uv": {
								"north": {"uv": [32, 32], "uv_size": [4, 2]},
								"east": {"uv": [32, 32], "uv_size": [2, 2]},
								"south": {"uv": [32, 32], "uv_size": [4, 2]},
								"west": {"uv": [32, 32], "uv_size": [2, 2]},
								"up": {"uv": [36, 34], "uv_size": [-4, -2]},
								"down": {"uv": [36, 34], "uv_size": [-4, -2]}
							}
						},
						{
							"origin": [-9, 0, -53],
							"size": [18, 2, 5],
							"uv": {
								"north": {"uv": [32, 32], "uv_size": [32, 4]},
								"east": {"uv": [32, 32], "uv_size": [4, 4]},
								"south": {"uv": [32, 32], "uv_size": [32, 4]},
								"west": {"uv": [32, 32], "uv_size": [4, 4]},
								"up": {"uv": [64, 36], "uv_size": [-32, -4]},
								"down": {"uv": [64, 36], "uv_size": [-32, -4]}
							}
						},
						{
							"origin": [6.45, 0, -51.9],
							"size": [5, 2, 7.1],
							"pivot": [8.9, 1, -49.5],
							"rotation": [0, 45, 0],
							"uv": {
								"north": {"uv": [64, 32], "uv_size": [-32, 4]},
								"east": {"uv": [36, 32], "uv_size": [-4, 4]},
								"south": {"uv": [64, 32], "uv_size": [-32, 4]},
								"west": {"uv": [36, 32], "uv_size": [-4, 4]},
								"up": {"uv": [32, 36], "uv_size": [32, -4]},
								"down": {"uv": [32, 36], "uv_size": [32, -4]}
							}
						},
						{
							"origin": [9, 0, -48],
							"size": [5, 2, 13],
							"uv": {
								"north": {"uv": [32, 32], "uv_size": [32, 4]},
								"east": {"uv": [32, 32], "uv_size": [4, 4]},
								"south": {"uv": [32, 32], "uv_size": [32, 4]},
								"west": {"uv": [32, 32], "uv_size": [4, 4]},
								"up": {"uv": [64, 36], "uv_size": [-32, -4]},
								"down": {"uv": [64, 36], "uv_size": [-32, -4]}
							}
						},
						{
							"origin": [-11.45, 0, -51.9],
							"size": [5, 2, 7.1],
							"pivot": [-8.9, 1, -49.5],
							"rotation": [0, -45, 0],
							"uv": {
								"north": {"uv": [32, 32], "uv_size": [32, 4]},
								"east": {"uv": [32, 32], "uv_size": [4, 4]},
								"south": {"uv": [32, 32], "uv_size": [32, 4]},
								"west": {"uv": [32, 32], "uv_size": [4, 4]},
								"up": {"uv": [64, 36], "uv_size": [-32, -4]},
								"down": {"uv": [64, 36], "uv_size": [-32, -4]}
							}
						},
						{
							"origin": [-14, 0, -48],
							"size": [5, 2, 13],
							"uv": {
								"north": {"uv": [32, 32], "uv_size": [32, 4]},
								"east": {"uv": [32, 32], "uv_size": [4, 4]},
								"south": {"uv": [32, 32], "uv_size": [32, 4]},
								"west": {"uv": [32, 32], "uv_size": [4, 4]},
								"up": {"uv": [64, 36], "uv_size": [-32, -4]},
								"down": {"uv": [64, 36], "uv_size": [-32, -4]}
							}
						},
						{
							"origin": [-14, 0, -17],
							"size": [28, 6, 3],
							"uv": {
								"north": {"uv": [32, 32], "uv_size": [32, 4]},
								"east": {"uv": [32, 32], "uv_size": [4, 4]},
								"south": {"uv": [32, 32], "uv_size": [32, 4]},
								"west": {"uv": [32, 32], "uv_size": [4, 4]},
								"up": {"uv": [64, 36], "uv_size": [-32, -4]},
								"down": {"uv": [64, 36], "uv_size": [-32, -4]}
							}
						},
						{
							"origin": [-9.7, 2.5, -27.8],
							"size": [23.4, 2, 4],
							"uv": {
								"north": {"uv": [32, 32], "uv_size": [32, 4]},
								"east": {"uv": [32, 32], "uv_size": [4, 4]},
								"south": {"uv": [32, 32], "uv_size": [32, 4]},
								"west": {"uv": [32, 32], "uv_size": [4, 4]},
								"up": {"uv": [64, 36], "uv_size": [-32, -4]},
								"down": {"uv": [64, 36], "uv_size": [-32, -4]}
							}
						},
						{
							"origin": [-6.7, 2.5, -38.8],
							"size": [13.4, 2, 3],
							"uv": {
								"north": {"uv": [32, 32], "uv_size": [32, 4]},
								"east": {"uv": [32, 32], "uv_size": [4, 4]},
								"south": {"uv": [32, 32], "uv_size": [32, 4]},
								"west": {"uv": [32, 32], "uv_size": [4, 4]},
								"up": {"uv": [64, 36], "uv_size": [-32, -4]},
								"down": {"uv": [64, 36], "uv_size": [-32, -4]}
							}
						},
						{
							"origin": [-6.7, 2.5, -47.8],
							"size": [13.4, 2, 3],
							"uv": {
								"north": {"uv": [32, 32], "uv_size": [32, 4]},
								"east": {"uv": [32, 32], "uv_size": [4, 4]},
								"south": {"uv": [32, 32], "uv_size": [32, 4]},
								"west": {"uv": [32, 32], "uv_size": [4, 4]},
								"up": {"uv": [64, 36], "uv_size": [-32, -4]},
								"down": {"uv": [64, 36], "uv_size": [-32, -4]}
							}
						}
					]
				},
				{
					"name": "trou",
					"parent": "Miner_MK1",
					"pivot": [0, 8, 0],
					"cubes": [
						{
							"origin": [-8, -7, -8],
							"size": [16, 14, 1],
							"uv": {
								"north": {"uv": [0, 32], "uv_size": [32, 28]},
								"east": {"uv": [0, 32], "uv_size": [4, 28]},
								"south": {"uv": [0, 32], "uv_size": [32, 28]},
								"west": {"uv": [0, 32], "uv_size": [4, 28]},
								"up": {"uv": [32, 36], "uv_size": [-32, -4]},
								"down": {"uv": [32, 36], "uv_size": [-32, -4]}
							}
						},
						{
							"origin": [-8, -7, -7],
							"size": [1, 14, 14],
							"uv": {
								"north": {"uv": [0, 32], "uv_size": [4, 28]},
								"east": {"uv": [0, 32], "uv_size": [32, 28]},
								"south": {"uv": [0, 32], "uv_size": [4, 28]},
								"west": {"uv": [0, 32], "uv_size": [32, 28]},
								"up": {"uv": [4, 64], "uv_size": [-4, -32]},
								"down": {"uv": [4, 64], "uv_size": [-4, -32]}
							}
						},
						{
							"origin": [7, -7, -7],
							"size": [1, 14, 14],
							"uv": {
								"north": {"uv": [0, 32], "uv_size": [4, 28]},
								"east": {"uv": [0, 32], "uv_size": [32, 28]},
								"south": {"uv": [0, 32], "uv_size": [4, 28]},
								"west": {"uv": [0, 32], "uv_size": [32, 28]},
								"up": {"uv": [4, 64], "uv_size": [-4, -32]},
								"down": {"uv": [4, 64], "uv_size": [-4, -32]}
							}
						},
						{
							"origin": [-8, -7, 7],
							"size": [16, 14, 1],
							"uv": {
								"north": {"uv": [0, 32], "uv_size": [32, 28]},
								"east": {"uv": [0, 32], "uv_size": [4, 28]},
								"south": {"uv": [0, 32], "uv_size": [32, 28]},
								"west": {"uv": [0, 32], "uv_size": [4, 28]},
								"up": {"uv": [32, 36], "uv_size": [-32, -4]},
								"down": {"uv": [32, 36], "uv_size": [-32, -4]}
							}
						}
					]
				}
			]
		}
	]
}